bullet/__init__.py
bullet/charDef.py
bullet/client.py
bullet/colors.py
bullet/cursor.py
bullet/emojis.py
bullet/keyhandler.py
bullet/styles.py
bullet/utils.py
winBullet-1.1.dist-info/LICENSE
winBullet-1.1.dist-info/METADATA
winBullet-1.1.dist-info/WHEEL
winBullet-1.1.dist-info/top_level.txt
winBullet-1.1.dist-info/RECORD
